{
  "type": "minecraft:crafting_shapeless",
  "category": "misc",
  "group": "locked_chest",
  "ingredients": [
    "minecraft:chest",
    "minecraft:purple_dye"
  ],
  "result": {
    "id": "minecraft:chest",
    "components": {
      "minecraft:lock": {
        "items": "minecraft:purple_dye"
      },
      "minecraft:lore": [
        {
          "color": "gray",
          "italic": false,
          "text": "Lock: "
        },
        {
          "color": "light_purple",
          "italic": false,
          "text": "minecraft:purple_dye"
        }
      ],
      "minecraft:container": [
        {
          "slot": 13,
          "item": {
            "id": "minecraft:purple_dye"
          }
        }
      ]
    }
  }
}